LICENSE.txt
MANIFEST.in
README.md
requirements.txt
setup.py
maskslic/__init__.py
maskslic/_slic.pyx
maskslic/_version.py
maskslic/feat_pca.py
maskslic/normalisation.py
maskslic/perfslic.py
maskslic/processing.pyx
maskslic/slic_superpixels.py
maskslic.egg-info/PKG-INFO
maskslic.egg-info/SOURCES.txt
maskslic.egg-info/dependency_links.txt
maskslic.egg-info/requires.txt
maskslic.egg-info/top_level.txt
src/Test.cpp
src/processing.cpp
src/processing.h