Metadata-Version: 2.1
Name: maskslic
Version: 0.3.4.post1
Summary: Simple linear iterative clustering (SLIC) in a region of interest (ROI)
Home-page: https://www.birving.com
Author: Benjamin Irving
Author-email: mail@birving.com
License: Copyright (C) 2016-2019, Benjamin Irving. See LICENSE file for distribution conditions
Classifier: Development Status :: 3 - Alpha
Classifier: Intended Audience :: Science/Research
Classifier: Programming Language :: Python :: 2.7
Classifier: Programming Language :: Python :: 3
Classifier: Topic :: Scientific/Engineering :: Bio-Informatics
Classifier: License :: Free for non-commercial use
License-File: LICENSE.txt
